cq/__init__.py
cq/exceptions.py
cq/py.typed
cq/_core/__init__.py
cq/_core/handler.py
cq/_core/message.py
cq/_core/middleware.py
cq/_core/pipetools.py
cq/_core/related_events.py
cq/_core/scope.py
cq/_core/dispatcher/__init__.py
cq/_core/dispatcher/base.py
cq/_core/dispatcher/bus.py
cq/_core/dispatcher/lazy.py
cq/_core/dispatcher/pipe.py
cq/ext/__init__.py
cq/ext/fastapi.py
cq/middlewares/__init__.py
cq/middlewares/retry.py
cq/middlewares/scope.py
python_cq-0.13.0.dist-info/METADATA
python_cq-0.13.0.dist-info/WHEEL
python_cq-0.13.0.dist-info/licenses/LICENSE
python_cq-0.13.0.dist-info/RECORD
