Metadata-Version: 2.4
Name: python-cq
Version: 0.13.0
Summary: CQRS library for async Python projects.
Project-URL: Documentation, https://python-cq.remimd.dev
Project-URL: Repository, https://github.com/100nm/python-cq
Author: remimd
License-Expression: MIT
License-File: LICENSE
Keywords: cqrs
Classifier: Development Status :: 4 - Beta
Classifier: Intended Audience :: Developers
Classifier: Natural Language :: English
Classifier: Operating System :: OS Independent
Classifier: Programming Language :: Python
Classifier: Programming Language :: Python :: 3
Classifier: Programming Language :: Python :: 3 :: Only
Classifier: Programming Language :: Python :: 3.12
Classifier: Programming Language :: Python :: 3.13
Classifier: Programming Language :: Python :: 3.14
Classifier: Topic :: Software Development :: Libraries
Classifier: Topic :: Software Development :: Libraries :: Application Frameworks
Classifier: Topic :: Software Development :: Libraries :: Python Modules
Classifier: Typing :: Typed
Requires-Python: <3.15,>=3.12
Requires-Dist: anyio
Requires-Dist: python-injection
Requires-Dist: type-analyzer
